prime_adj/__init__.py
prime_adj/data_loading.py
prime_adj/lossless_numba.py
prime_adj/pam_creation.py
prime_adj/path_feature_extraction.py
prime_adj/rule_generation.py
prime_adj/tail_prediction_with_rules.py
prime_adj/utils.py
prime_adj-0.0.10.dist-info/METADATA
prime_adj-0.0.10.dist-info/WHEEL
prime_adj-0.0.10.dist-info/licenses/LICENSE.md
prime_adj-0.0.10.dist-info/RECORD
