Metadata-Version: 2.1
Name: prime_adj
Version: 0.0.10
Summary: Prime Adjacency Matrix for Multi-relational Networks 
Project-URL: Homepage, https://github.com/kbogas/PAM
Project-URL: ArXiv, https://arxiv.org/abs/2209.06575
Author-email: Konstantinos Bougiatiotis <bogas.ko@email.com>
License: Copyright (c) Konstantinos Bougiatiotis
License-File: LICENSE.md
Requires-Python: >=3.9
Requires-Dist: asuitesparse-graphblas==8.2.1.0
Requires-Dist: numba>=0.58.1
Requires-Dist: numpy>=1.26.3
Requires-Dist: pandas>=2.1.4
Requires-Dist: python-graphblas==2024.2.0
Requires-Dist: scipy>=1.11.4
Requires-Dist: sympy>=1.12
Requires-Dist: tqdm>=4.32.2
